globefish/core.py
globefish/utilities.py
globefish/__init__.py
globefish-0.0.1.dist-info/DESCRIPTION.rst
globefish-0.0.1.dist-info/METADATA
globefish-0.0.1.dist-info/metadata.json
globefish-0.0.1.dist-info/RECORD
globefish-0.0.1.dist-info/top_level.txt
globefish-0.0.1.dist-info/WHEEL
