Metadata-Version: 2.0
Name: globefish
Version: 0.0.1
Summary: A Python Web Framework.
Home-page: UNKNOWN
Author: ladder1984
Author-email: ladder1984@gmail.com
License: MIT
Platform: UNKNOWN
Requires-Dist: Jinja2 (>=2.4)
